simtoolsz/__init__.py
simtoolsz/datetime.py
simtoolsz/db.py
simtoolsz/mail.py
simtoolsz/reader.py
simtoolsz/utils.py
simtoolsz-0.2.8.dist-info/METADATA
simtoolsz-0.2.8.dist-info/WHEEL
simtoolsz-0.2.8.dist-info/licenses/LICENSE
simtoolsz-0.2.8.dist-info/RECORD
