Metadata-Version: 2.3
Name: simtoolsz
Version: 0.2.8
Summary: A simple and convenient toolkit containing useful functions, classes, and methods.
Project-URL: Homepage, https://github.com/SidneyLYZhang/simtoolsz
Project-URL: Repository, https://github.com/SidneyLYZhang/simtoolsz.git
Project-URL: Issues, https://github.com/SidneyLYZhang/simtoolsz/issues
Author-email: Sidney Zhang <liangyi@me.com>
License: MulanPSL-2.0
Keywords: collection,tool
Classifier: Development Status :: 4 - Beta
Classifier: License :: OSI Approved :: Mulan Permissive Software License v2 (MulanPSL-2.0)
Classifier: Operating System :: OS Independent
Classifier: Programming Language :: Python :: 3
Classifier: Programming Language :: Python :: 3.11
Classifier: Programming Language :: Python :: 3.12
Classifier: Programming Language :: Python :: 3.13
Classifier: Topic :: Software Development :: Libraries :: Python Modules
Requires-Python: >=3.11
Requires-Dist: duckdb>=1.4.0
Requires-Dist: pendulum>=3.1.0
Requires-Dist: polars>=1.33.1
